{
  "Object": {
    "GUID": "514559",
    "Name": "Custom_Tile",
    "Transform": {
      "posX": -6.93788767,
      "posY": 2.18782568,
      "posZ": 72.1386,
      "rotX": 0.000006235811,
      "rotY": 179.999771,
      "rotZ": 3.2736132e-8,
      "scaleX": 1.70145762,
      "scaleY": 1,
      "scaleZ": 1.70145762
    },
    "Nickname": "Princess Irulan",
    "Description": "",
    "GMNotes": "",
    "AltLookAngle": {
      "x": 0,
      "y": 0,
      "z": 0
    },
    "ColorDiffuse": {
      "r": 0,
      "g": 0,
      "b": 0
    },
    "Tags": [
      "Leader"
    ],
    "LayoutGroupSortIndex": 0,
    "Value": 0,
    "Locked": false,
    "Grid": true,
    "Snap": true,
    "IgnoreFoW": false,
    "MeasureMovement": false,
    "DragSelectable": true,
    "Autoraise": true,
    "Sticky": true,
    "Tooltip": false,
    "GridProjection": false,
    "HideWhenFaceDown": false,
    "Hands": false,
    "CustomImage": {
      "ImageURL": "https://steamusercontent-a.akamaihd.net/ugc/1892102591129981570/F4A67B5483EE039A60B4D6B7A4637B82CD448F16/",
      "ImageSecondaryURL": "",
      "ImageScalar": 1,
      "WidthScale": 0,
      "CustomTile": {
        "Type": 3,
        "Thickness": 0.1,
        "Stackable": false,
        "Stretch": true
      }
    },
    "LuaScript": "#include ./Princess_Irulan.514559.lua",
    "LuaScriptState": "",
    "XmlUI": ""
  },
  "StatesPaths": {}
}
