{
  "Object": {
    "GUID": "6d8a2e",
    "Name": "ScriptingTrigger",
    "Transform": {
      "posX": 13.785943,
      "posY": 2.16416049,
      "posZ": 20.7533684,
      "rotX": 0.0200061426,
      "rotY": 359.927948,
      "rotZ": 0.06999992,
      "scaleX": 2.98461127,
      "scaleY": 1.04195046,
      "scaleZ": 3.76548815
    },
    "Nickname": "",
    "Description": "",
    "GMNotes": "",
    "AltLookAngle": {
      "x": 0,
      "y": 0,
      "z": 0
    },
    "ColorDiffuse": {
      "r": 1,
      "g": 1,
      "b": 1,
      "a": 0.509803951
    },
    "LayoutGroupSortIndex": 0,
    "Value": 0,
    "Locked": true,
    "Grid": true,
    "Snap": true,
    "IgnoreFoW": false,
    "MeasureMovement": false,
    "DragSelectable": true,
    "Autoraise": true,
    "Sticky": true,
    "Tooltip": true,
    "GridProjection": false,
    "HideWhenFaceDown": false,
    "Hands": false,
    "LuaScript": "",
    "LuaScriptState": "",
    "XmlUI": ""
  },
  "StatesPaths": {}
}
